azure/mgmt/selfhelp/__init__.py
azure/mgmt/selfhelp/_configuration.py
azure/mgmt/selfhelp/_patch.py
azure/mgmt/selfhelp/_self_help_mgmt_client.py
azure/mgmt/selfhelp/_serialization.py
azure/mgmt/selfhelp/_vendor.py
azure/mgmt/selfhelp/_version.py
azure/mgmt/selfhelp/py.typed
azure/mgmt/selfhelp/aio/__init__.py
azure/mgmt/selfhelp/aio/_configuration.py
azure/mgmt/selfhelp/aio/_patch.py
azure/mgmt/selfhelp/aio/_self_help_mgmt_client.py
azure/mgmt/selfhelp/aio/operations/__init__.py
azure/mgmt/selfhelp/aio/operations/_diagnostics_operations.py
azure/mgmt/selfhelp/aio/operations/_discovery_solution_operations.py
azure/mgmt/selfhelp/aio/operations/_operations.py
azure/mgmt/selfhelp/aio/operations/_patch.py
azure/mgmt/selfhelp/models/__init__.py
azure/mgmt/selfhelp/models/_models_py3.py
azure/mgmt/selfhelp/models/_patch.py
azure/mgmt/selfhelp/models/_self_help_mgmt_client_enums.py
azure/mgmt/selfhelp/operations/__init__.py
azure/mgmt/selfhelp/operations/_diagnostics_operations.py
azure/mgmt/selfhelp/operations/_discovery_solution_operations.py
azure/mgmt/selfhelp/operations/_operations.py
azure/mgmt/selfhelp/operations/_patch.py
azure_mgmt_selfhelp-1.0.0.dist-info/LICENSE
azure_mgmt_selfhelp-1.0.0.dist-info/METADATA
azure_mgmt_selfhelp-1.0.0.dist-info/WHEEL
azure_mgmt_selfhelp-1.0.0.dist-info/top_level.txt
azure_mgmt_selfhelp-1.0.0.dist-info/RECORD
